holidays_ext/__init__.py
holidays_ext/get_holidays.py
holidays_ext/holidays_ext.py
holidays_ext-0.0.8.dist-info/LICENSE
holidays_ext-0.0.8.dist-info/METADATA
holidays_ext-0.0.8.dist-info/WHEEL
holidays_ext-0.0.8.dist-info/top_level.txt
holidays_ext-0.0.8.dist-info/RECORD
