Metadata-Version: 2.1
Name: holidays-ext
Version: 0.0.8
Summary: Extended holidays package
Home-page: https://github.com/kaixuyang/holidays-extension
Author: Kaixu Yang
Author-email: kaixuyang@gmail.com
License: MIT
Classifier: Programming Language :: Python
Classifier: Programming Language :: Python :: 3
Classifier: Programming Language :: Python :: 3.7
Requires-Python: >=3
License-File: LICENSE
Requires-Dist: numpy (>=1.15.4)
Requires-Dist: pandas (>=1.0.4)
Requires-Dist: python-dateutil (>=2.8.0)
Requires-Dist: LunarCalendar-ext (>=0.0.1)
Requires-Dist: convertdate (>=2.1.2)
Requires-Dist: holidays (>=0.9.5)
